dlsite_async-0.9.0.dist-info/METADATA
dlsite_async-0.9.0.dist-info/WHEEL
dlsite_async-0.9.0.dist-info/entry_points.txt
dlsite_async-0.9.0.dist-info/licenses/LICENSE
dlsite_async/__init__.py
dlsite_async/_scraper.py
dlsite_async/api.py
dlsite_async/circle.py
dlsite_async/exceptions.py
dlsite_async/play/__init__.py
dlsite_async/play/api.py
dlsite_async/play/ebook.py
dlsite_async/play/epub.py
dlsite_async/play/models.py
dlsite_async/play/scramble.py
dlsite_async/py.typed
dlsite_async/utils.py
dlsite_async/work.py
dlsite_async-0.9.0.dist-info/RECORD
