Metadata-Version: 2.1
Name: dlsite-async
Version: 0.9.0
Summary: DLsite Async
Author-Email: byeonhyeok <bhrevol@gmail.com>
License: MIT
Classifier: Development Status :: 4 - Beta
Project-URL: Changelog, https://github.com/bhrevol/dlsite-async/releases
Project-URL: homepage, https://github.com/bhrevol/dlsite-async
Project-URL: repository, https://github.com/bhrevol/dlsite-async
Project-URL: documentation, https://dlsite-async.readthedocs.io
Requires-Python: <4.0,>=3.11
Requires-Dist: lxml>=5.3.0
Requires-Dist: aiohttp<4.0.0,>=3.8.1
Requires-Dist: beautifulsoup4<5.0.0,>=4.11.1
Requires-Dist: cryptography>=44.0.0
Provides-Extra: pil
Requires-Dist: Pillow>=11.0.0; extra == "pil"
